llama_index/multi_modal_llms/anthropic/__init__.py
llama_index/multi_modal_llms/anthropic/base.py
llama_index/multi_modal_llms/anthropic/utils.py
llama_index_multi_modal_llms_anthropic-0.4.1.dist-info/METADATA
llama_index_multi_modal_llms_anthropic-0.4.1.dist-info/WHEEL
llama_index_multi_modal_llms_anthropic-0.4.1.dist-info/licenses/LICENSE
llama_index_multi_modal_llms_anthropic-0.4.1.dist-info/RECORD
