Metadata-Version: 2.4
Name: llama-index-multi-modal-llms-anthropic
Version: 0.4.1
Summary: llama-index multi-modal-llms anthropic integration
Author-email: Your Name <you@example.com>
License-Expression: MIT
License-File: LICENSE
Requires-Python: <4.0,>=3.9
Requires-Dist: anthropic>=0.34.2
Requires-Dist: filetype<2,>=1.2.0
Requires-Dist: llama-index-core<0.15,>=0.13.0
Requires-Dist: llama-index-llms-anthropic<0.9,>=0.8.0
